receptus/__init__.py
receptus/receptus.py
receptus-0.1.4.dist-info/licenses/LICENSE
receptus-0.1.4.dist-info/METADATA
receptus-0.1.4.dist-info/WHEEL
receptus-0.1.4.dist-info/top_level.txt
receptus-0.1.4.dist-info/RECORD
