Metadata-Version: 2.4
Name: receptus
Version: 0.1.4
Summary: A flexible, interactive command-line prompt toolkit for Python.
Author-email: James Husted <james@husted.dev>
License-Expression: MIT
Project-URL: Homepage, https://github.com/HusteDev/receptus
Classifier: Programming Language :: Python :: 3
Classifier: Operating System :: OS Independent
Classifier: Development Status :: 4 - Beta
Classifier: Intended Audience :: Developers
Classifier: Topic :: Software Development :: Libraries :: Python Modules
Classifier: Topic :: Terminals
Requires-Python: >=3.7
License-File: LICENSE
Requires-Dist: colorama
Requires-Dist: inputimeout; sys_platform == "win32"
Dynamic: license-file
